doc_to_benchmark/__init__.py
doc_to_benchmark/__main__.py
doc_to_benchmark/cli.py
doc_to_benchmark/database.py
doc_to_benchmark/generate_benchmark.py
doc_to_benchmark/models.py
doc_to_benchmark/ocr_pipeline.py
doc_to_benchmark/pdf_processing.py
doc_to_benchmark/schemas.py
doc_to_benchmark/seed_data.py
doc_to_benchmark/storage.py
doc_to_benchmark/api/__init__.py
doc_to_benchmark/api/dependencies.py
doc_to_benchmark/api/routes.py
doc_to_benchmark/ocr_agent/__init__.py
doc_to_benchmark/ocr_agent/config.py
doc_to_benchmark/ocr_agent/graph.py
doc_to_benchmark/ocr_agent/main.py
doc_to_benchmark/ocr_agent/state.py
doc_to_benchmark/ocr_agent/agents/__init__.py
doc_to_benchmark/ocr_agent/agents/basic_extraction_agent.py
doc_to_benchmark/ocr_agent/agents/judge_agent.py
doc_to_benchmark/ocr_agent/agents/report_generator.py
doc_to_benchmark/ocr_agent/agents/validation_agent.py
doc_to_benchmark/ocr_agent/prompts/__init__.py
doc_to_benchmark/ocr_agent/prompts/judge_prompts.py
doc_to_benchmark/ocr_agent/prompts/validation_prompts.py
doc_to_benchmark/ocr_agent/tools/__init__.py
doc_to_benchmark/ocr_agent/tools/custom_split_tool.py
doc_to_benchmark/ocr_agent/tools/layout_parser_tool.py
doc_to_benchmark/ocr_agent/tools/pdfminer_tool.py
doc_to_benchmark/ocr_agent/tools/pdfplumber_tool.py
doc_to_benchmark/ocr_agent/tools/pypdfium2_tool.py
doc_to_benchmark/ocr_agent/tools/table_enhancement_tool.py
doc_to_benchmark/ocr_agent/tools/upstage_document_parse_tool.py
doc_to_benchmark/ocr_agent/tools/upstage_ocr_tool.py
doc_to_benchmark/ocr_agent/utils/__init__.py
doc_to_benchmark/ocr_agent/utils/file_utils.py
doc_to_benchmark/ocr_agent/utils/llm_client.py
doc_to_benchmark/ocr_agent/utils/metrics.py
doc_to_benchmark/static/index.html
doc_to_benchmark/static/vite.svg
doc_to_benchmark/static/assets/index-BZ29wlRN.css
doc_to_benchmark/static/assets/index-CwS5OJKv.js
doc_to_benchmark-0.1.0.dist-info/METADATA
doc_to_benchmark-0.1.0.dist-info/WHEEL
doc_to_benchmark-0.1.0.dist-info/entry_points.txt
doc_to_benchmark-0.1.0.dist-info/top_level.txt
doc_to_benchmark-0.1.0.dist-info/RECORD
