Metadata-Version: 2.4
Name: doc-to-benchmark
Version: 0.1.0
Summary: FastAPI + React file upload demo packaged for PyPI distribution
Home-page: https://github/yoonth95/doc-to-benchmark
Author: Your Name
Classifier: Programming Language :: Python :: 3
Classifier: Framework :: FastAPI
Classifier: License :: OSI Approved :: MIT License
Classifier: Operating System :: OS Independent
Requires-Python: >=3.10
Requires-Dist: fastapi>=0.115.5
Requires-Dist: numpy>=1.24
Requires-Dist: opencv-python-headless>=4.8
Requires-Dist: Pillow>=10.0
Requires-Dist: PyMuPDF>=1.24.0
Requires-Dist: PyPDF2>=3.0.0
Requires-Dist: langgraph>=0.6.0
Requires-Dist: pdfplumber>=0.11.0
Requires-Dist: pdfminer.six>=20231206
Requires-Dist: pypdf>=4.0.0
Requires-Dist: pypdfium2>=4.30.0
Requires-Dist: requests>=2.31.0
Requires-Dist: python-dotenv>=1.0.0
Requires-Dist: SQLAlchemy>=2.0
Requires-Dist: aiosqlite>=0.19
Requires-Dist: uvicorn>=0.32.1
Requires-Dist: python-multipart>=0.0.20
Requires-Dist: transformers>=4.36.2
Requires-Dist: huggingface_hub>=0.15.0
Requires-Dist: datasets>=2.16.2
Requires-Dist: faiss-cpu>=1.7.4
Requires-Dist: pydantic>=2.5.2
Requires-Dist: openai>=1.42.1
Dynamic: author
Dynamic: classifier
Dynamic: description
Dynamic: description-content-type
Dynamic: home-page
Dynamic: requires-dist
Dynamic: requires-python
Dynamic: summary
